{
    "day": [ 
{
    "url": "https://firebasestorage.googleapis.com/v0/b/alexandraciausu-a6df7.appspot.com/o/machiaj-de-zi%2F1.jpg?alt=media"
}
    ],
    "night": [
        {
            "url":"https://firebasestorage.googleapis.com/v0/b/alexandraciausu-a6df7.appspot.com/o/machiaj-de-zi%2F1.jpg?alt=media"
        }
    ],
    "bridal": [
        {
            "url":"https://firebasestorage.googleapis.com/v0/b/alexandraciausu-a6df7.appspot.com/o/machiaj-de-zi%2F1.jpg?alt=media"
        }
    ],
    "special": [
        {
            "url":"https://firebasestorage.googleapis.com/v0/b/alexandraciausu-a6df7.appspot.com/o/machiaj-de-zi%2F1.jpg?alt=media"
        }
    ]
}